wscounter/__init__.py
wscounter/apps.py
wscounter/data.py
wscounter/test.py
wscounter/tests.py
wscounter/urls.py
wscounter/utils.py
wscounter/views.py
django_wscounter-0.1.5.1.dist-info/METADATA
django_wscounter-0.1.5.1.dist-info/WHEEL
django_wscounter-0.1.5.1.dist-info/top_level.txt
django_wscounter-0.1.5.1.dist-info/RECORD
