Metadata-Version: 2.1
Name: django-wscounter
Version: 0.1.5.1
Summary: A dynamic web-socket
Home-page: https://github.com/salalem/django-wscounter/
Author: Firas Al Kafri
Author-email: firas.alkafri@gmail.com
License: GPLv2
Platform: UNKNOWN
Requires-Dist: cerberus (>=1.1)
